relations_postgresql/__init__.py
relations_postgresql/clause.py
relations_postgresql/column.py
relations_postgresql/criteria.py
relations_postgresql/criterion.py
relations_postgresql/ddl.py
relations_postgresql/expression.py
relations_postgresql/index.py
relations_postgresql/query.py
relations_postgresql/sql.py
relations_postgresql/table.py
relations_postgresql-0.6.2.dist-info/LICENSE.txt
relations_postgresql-0.6.2.dist-info/METADATA
relations_postgresql-0.6.2.dist-info/WHEEL
relations_postgresql-0.6.2.dist-info/top_level.txt
relations_postgresql-0.6.2.dist-info/RECORD
